pubmed_fetcher/__init.py
pubmed_fetcher/cli.py
pubmed_fetcher/client.py
pubmed_fetcher/exceptions.py
pubmed_fetcher/fetcher.py
pubmed_fetcher/models.py
pubmed_fetcher/processor.py
pubmed_fetcher_sk172002-0.1.0.dist-info/entry_points.txt
pubmed_fetcher_sk172002-0.1.0.dist-info/METADATA
pubmed_fetcher_sk172002-0.1.0.dist-info/WHEEL
pubmed_fetcher_sk172002-0.1.0.dist-info/RECORD
