Metadata-Version: 2.3
Name: pubmed-fetcher-sk172002
Version: 0.1.0
Summary: A tool by Sanjay for fetching papers from PubMed
License: MIT
Author: sxnjayy
Author-email: 104524087+skp6850@users.noreply.github.com
Requires-Python: >=3.12
Classifier: License :: OSI Approved :: MIT License
Classifier: Programming Language :: Python :: 3
Classifier: Programming Language :: Python :: 3.12
Classifier: Programming Language :: Python :: 3.13
Requires-Dist: biopython (>=1.81,<2.0.0)
Requires-Dist: pandas (>=2.2.3,<3.0.0)
Requires-Dist: pytest (>=8.3.5,<9.0.0)
Requires-Dist: requests (>=2.32.3,<3.0.0)
Requires-Dist: tqdm (>=4.67.1,<5.0.0)
